netdata_insights/__init__.py
netdata_insights/_nbdev.py
netdata_insights/correlations/__init__.py
netdata_insights/correlations/core.py
netdata_insights/correlations/ks.py
netdata_insights/correlations/utils.py
netdata_insights/data/__init__.py
netdata_insights/data/core.py
netdata_insights/data/preprocessing.py
netdata_insights/data/utils.py
netdata_insights/sample_data/__init__.py
netdata_insights_alt-0.1.21.dist-info/LICENSE
netdata_insights_alt-0.1.21.dist-info/METADATA
netdata_insights_alt-0.1.21.dist-info/WHEEL
netdata_insights_alt-0.1.21.dist-info/entry_points.txt
netdata_insights_alt-0.1.21.dist-info/top_level.txt
netdata_insights_alt-0.1.21.dist-info/RECORD
