Metadata-Version: 2.1
Name: netdata-insights-alt
Version: 0.1.21
Summary: Python library for Netdata 'Insights' features.
Home-page: https://github.com/netdata/netdata-insights/tree/master/
Author: Andrew Maguire
Author-email: andrewmaguire@netdata.cloud
License: Apache Software License 2.0
Keywords: netdata
Platform: UNKNOWN
Classifier: Development Status :: 3 - Alpha
Classifier: Intended Audience :: Developers
Classifier: License :: OSI Approved :: Apache Software License
Classifier: Natural Language :: English
Classifier: Programming Language :: Python :: 3.6
Classifier: Programming Language :: Python :: 3.7
Classifier: Programming Language :: Python :: 3.8
Requires-Python: >=3.6
Requires-Dist: pandas (==1.0.4)
Requires-Dist: numpy (==1.18.5)
Requires-Dist: scipy (==1.5.1)
Requires-Dist: requests (==2.24.0)
